saltext/vector/__init__.py
saltext/vector/version.py
saltext/vector/engines/__init__.py
saltext/vector/engines/vector.py
saltext.vector-0.0.6.dist-info/METADATA
saltext.vector-0.0.6.dist-info/WHEEL
saltext.vector-0.0.6.dist-info/entry_points.txt
saltext.vector-0.0.6.dist-info/top_level.txt
saltext.vector-0.0.6.dist-info/RECORD
